setup.py
sga/__init__.py
sga/constants.py
sga/django_ga.py
sga/flask_ga.py
sga/ga_adapter.py
sga/ga_agent.py
sga/kola_ga.py
sga.egg-info/PKG-INFO
sga.egg-info/SOURCES.txt
sga.egg-info/dependency_links.txt
sga.egg-info/not-zip-safe
sga.egg-info/requires.txt
sga.egg-info/top_level.txt
sga/bin/run_ga_agent.py