Metadata-Version: 1.0
Name: sga
Version: 0.1.36
Summary: make it easier to use pyga for web develop. and make pyga compatible with flask and django.
Home-page: https://github.com/dantezhu/sga
Author: dantezhu
Author-email: zny2008@gmail.com
License: BSD
Platform: any
